[
  {
    "id": "cmmb5jeme0007m26k266a8i7z",
    "snapshotDate": "2026-03-03",
    "userId": "cmmb46i64002im2q08tv0dw6y",
    "streak": 2,
    "lastDevotionalDateCompleted": null,
    "totalDevotionalsCompleted": 6,
    "updatedAt": "2026-03-03T22:23:39.014Z"
  },
  {
    "id": "cmmb5jem90006m26kd3x40pte",
    "snapshotDate": "2026-03-03",
    "userId": "cmmb3ggjr001jm2q06al9hwcz",
    "streak": 1,
    "lastDevotionalDateCompleted": null,
    "totalDevotionalsCompleted": 1,
    "updatedAt": "2026-03-03T22:23:39.011Z"
  },
  {
    "id": "cmmat7pxa0005m25cue8wpl3f",
    "snapshotDate": "2026-03-03",
    "userId": "cmmaqp77i000pm2686xq6bozg",
    "streak": 1,
    "lastDevotionalDateCompleted": null,
    "totalDevotionalsCompleted": 2,
    "updatedAt": "2026-03-03T22:23:39.009Z"
  },
  {
    "id": "cmma4877o0004m2uragnc2lrf",
    "snapshotDate": "2026-03-03",
    "userId": "cmma36c8v000qm25km7avpj84",
    "streak": 6,
    "lastDevotionalDateCompleted": null,
    "totalDevotionalsCompleted": 7,
    "updatedAt": "2026-03-03T22:23:39.004Z"
  },
  {
    "id": "cmm9zo92s001ym29qppdrb37o",
    "snapshotDate": "2026-03-03",
    "userId": "cmm9yc1nx000sm29qq8qeoai9",
    "streak": 9,
    "lastDevotionalDateCompleted": null,
    "totalDevotionalsCompleted": 8,
    "updatedAt": "2026-03-03T22:23:39.001Z"
  },
  {
    "id": "cmm9zo92q001xm29qr7dto06q",
    "snapshotDate": "2026-03-03",
    "userId": "cmm9y71p5000km29qqx44tb91",
    "streak": 4,
    "lastDevotionalDateCompleted": null,
    "totalDevotionalsCompleted": 5,
    "updatedAt": "2026-03-03T22:23:38.998Z"
  },
  {
    "id": "cmm9xoav90001m29qwzjzu5sj",
    "snapshotDate": "2026-03-03",
    "userId": "cmm9x0ybc0002m2sr3l31uj4q",
    "streak": 25,
    "lastDevotionalDateCompleted": null,
    "totalDevotionalsCompleted": 8,
    "updatedAt": "2026-03-03T22:23:38.994Z"
  },
  {
    "id": "cmm9wz7ya0007m2ljwetxq5cc",
    "snapshotDate": "2026-03-03",
    "userId": "cmm9wyrup0000m2ljk2gdacr0",
    "streak": 0,
    "lastDevotionalDateCompleted": null,
    "totalDevotionalsCompleted": 0,
    "updatedAt": "2026-03-03T22:23:38.977Z"
  }
]